{
    "id": 117,
    "ref": "Trạm thu phí",
    "hData": {
        "117-0": {
            "id": "117-0",
            "name": "Trạm thu phí IC 12.3",
            "nodes": [[104.892324, 21.646329]],
            "bounds": [
                [21.644869, 104.891464],
                [21.644869, 104.89311],
                [21.647521, 104.89311],
                [21.647521, 104.891464]
            ],
            "buffer_geometry": [
                [21.646823, 104.891582],
                [21.646145, 104.892075],
                [21.645527, 104.892483],
                [21.644953, 104.892853],
                [21.644869, 104.892939],
                [21.644983, 104.89311],
                [21.64619, 104.892692],
                [21.646674, 104.892563],
                [21.647521, 104.892209],
                [21.647167, 104.891769],
                [21.646958, 104.891464]
            ]
        }
    },
    "keyData": {
        "104.89_21.64__104.90_21.65": ["117-0"],
        "21.64_104.89__21.65_104.90": ["117-0"]
    },
    "highways": [
        {
            "highway_name": "Trạm thu phí IC 12.3",
            "ways": [
                {
                    "nodes": [[104.892324, 21.646329]],
                    "buffer_geometry": [
                        [21.646823, 104.891582],
                        [21.646145, 104.892075],
                        [21.645527, 104.892483],
                        [21.644953, 104.892853],
                        [21.644869, 104.892939],
                        [21.644983, 104.89311],
                        [21.64619, 104.892692],
                        [21.646674, 104.892563],
                        [21.647521, 104.892209],
                        [21.647167, 104.891769],
                        [21.646958, 104.891464]
                    ]
                }
            ]
        }
    ]
}
