{
    "id": 67,
    "ref": "Trạm thu phí",
    "hData": {
        "67-0": {
            "id": "67-0",
            "name": "Trạm Thu Phí Cao tốc Hà Nội - Hải Phòng( Đình Vũ)",
            "nodes": [[106.746562, 20.787344]],
            "bounds": [
                [20.77682, 106.73353],
                [20.77682, 106.754858],
                [20.801354, 106.754858],
                [20.801354, 106.73353]
            ],
            "buffer_geometry": [
                [20.781033, 106.73353],
                [20.788816, 106.747949],
                [20.794654, 106.750717],
                [20.796459, 106.750867],
                [20.798124, 106.750932],
                [20.798706, 106.750932],
                [20.799528, 106.75076],
                [20.801213, 106.750588],
                [20.801354, 106.754794],
                [20.799709, 106.754537],
                [20.798064, 106.754708],
                [20.795657, 106.754858],
                [20.791986, 106.75458],
                [20.78685, 106.752756],
                [20.781634, 106.746941],
                [20.779528, 106.742005],
                [20.77682, 106.736877],
                [20.778685, 106.735568]
            ]
        }
    },
    "keyData": {
        "106.74_20.78__106.75_20.79": ["67-0"],
        "20.78_106.73__20.79_106.74": ["67-0"],
        "20.78_106.74__20.79_106.75": ["67-0"],
        "20.79_106.74__20.80_106.75": ["67-0"],
        "20.79_106.75__20.80_106.76": ["67-0"],
        "20.80_106.75__20.81_106.76": ["67-0"],
        "20.78_106.75__20.79_106.76": ["67-0"],
        "20.77_106.74__20.78_106.75": ["67-0"],
        "20.77_106.73__20.78_106.74": ["67-0"]
    },
    "highways": [
        {
            "highway_name": "Trạm Thu Phí Cao tốc Hà Nội - Hải Phòng( Đình Vũ)",
            "ways": [
                {
                    "nodes": [[106.746562, 20.787344]],
                    "buffer_geometry": [
                        [20.781033, 106.73353],
                        [20.788816, 106.747949],
                        [20.794654, 106.750717],
                        [20.796459, 106.750867],
                        [20.798124, 106.750932],
                        [20.798706, 106.750932],
                        [20.799528, 106.75076],
                        [20.801213, 106.750588],
                        [20.801354, 106.754794],
                        [20.799709, 106.754537],
                        [20.798064, 106.754708],
                        [20.795657, 106.754858],
                        [20.791986, 106.75458],
                        [20.78685, 106.752756],
                        [20.781634, 106.746941],
                        [20.779528, 106.742005],
                        [20.77682, 106.736877],
                        [20.778685, 106.735568]
                    ]
                }
            ]
        }
    ]
}
